{
	"$schema": "http://schema.management.azure.com/schemas/2015-01-01/deploymentTemplate.json#",
	"contentVersion": "1.0.0.0",
	"parameters": {
		"factoryName": {
			"type": "string",
			"metadata": "Data Factory name",
			"defaultValue": "adf-subsidio-etl-griz"
		}
	},
	"variables": {
		"factoryId": "[concat('Microsoft.DataFactory/factories/', parameters('factoryName'))]"
	},
	"resources": [
		{
			"name": "[concat(parameters('factoryName'), '/ds_sql_silver_as_entregas')]",
			"type": "Microsoft.DataFactory/factories/datasets",
			"apiVersion": "2018-06-01",
			"properties": {
				"linkedServiceName": {
					"referenceName": "ls_azure_sql_dw_dest",
					"type": "LinkedServiceReference"
				},
				"folder": {
					"name": "silver/AS"
				},
				"annotations": [],
				"type": "AzureSqlTable",
				"schema": [
					{
						"name": "entrega_id",
						"type": "int",
						"precision": 10
					},
					{
						"name": "boleta_id",
						"type": "int",
						"precision": 10
					},
					{
						"name": "ci_beneficiaria",
						"type": "varchar"
					},
					{
						"name": "establecimiento_id",
						"type": "int",
						"precision": 10
					},
					{
						"name": "paquete_id",
						"type": "int",
						"precision": 10
					},
					{
						"name": "paquete_nombre",
						"type": "varchar"
					},
					{
						"name": "fecha_entrega",
						"type": "date"
					},
					{
						"name": "lote_produccion",
						"type": "varchar"
					},
					{
						"name": "peso_paquete_kg",
						"type": "decimal",
						"precision": 10,
						"scale": 2
					},
					{
						"name": "fecha_proxima_entrega",
						"type": "date"
					}
				],
				"typeProperties": {
					"schema": "silver",
					"table": "as_entregas"
				}
			},
			"dependsOn": []
		},
		{
			"name": "[concat(parameters('factoryName'), '/ds_sql_silver_as_recepciones')]",
			"type": "Microsoft.DataFactory/factories/datasets",
			"apiVersion": "2018-06-01",
			"properties": {
				"linkedServiceName": {
					"referenceName": "ls_azure_sql_dw_dest",
					"type": "LinkedServiceReference"
				},
				"folder": {
					"name": "silver/AS"
				},
				"annotations": [],
				"type": "AzureSqlTable",
				"schema": [
					{
						"name": "recepcion_id",
						"type": "int",
						"precision": 10
					},
					{
						"name": "nro_lote",
						"type": "varchar"
					},
					{
						"name": "condicion",
						"type": "varchar"
					},
					{
						"name": "estado",
						"type": "varchar"
					},
					{
						"name": "almacen_id",
						"type": "int",
						"precision": 10
					},
					{
						"name": "transportista_id",
						"type": "int",
						"precision": 10
					},
					{
						"name": "vehiculo_id",
						"type": "int",
						"precision": 10
					},
					{
						"name": "fecha_recepcion",
						"type": "date"
					},
					{
						"name": "cantidad_recibida",
						"type": "decimal",
						"precision": 18,
						"scale": 2
					},
					{
						"name": "unidad",
						"type": "varchar"
					},
					{
						"name": "responsable",
						"type": "varchar"
					},
					{
						"name": "nro_guia_remision",
						"type": "varchar"
					},
					{
						"name": "temperatura_llegada",
						"type": "decimal",
						"precision": 5,
						"scale": 2
					}
				],
				"typeProperties": {
					"schema": "silver",
					"table": "as_recepciones"
				}
			},
			"dependsOn": []
		},
		{
			"name": "[concat(parameters('factoryName'), '/ds_sql_silver_as_transportistas')]",
			"type": "Microsoft.DataFactory/factories/datasets",
			"apiVersion": "2018-06-01",
			"properties": {
				"linkedServiceName": {
					"referenceName": "ls_azure_sql_dw_dest",
					"type": "LinkedServiceReference"
				},
				"folder": {
					"name": "silver/AS"
				},
				"annotations": [],
				"type": "AzureSqlTable",
				"schema": [
					{
						"name": "transportista_id",
						"type": "int",
						"precision": 10
					},
					{
						"name": "razon_social",
						"type": "varchar"
					},
					{
						"name": "nit",
						"type": "varchar"
					},
					{
						"name": "municipio",
						"type": "varchar"
					},
					{
						"name": "contacto",
						"type": "varchar"
					},
					{
						"name": "telefono",
						"type": "varchar"
					},
					{
						"name": "estado",
						"type": "varchar"
					}
				],
				"typeProperties": {
					"schema": "silver",
					"table": "as_transportistas"
				}
			},
			"dependsOn": []
		},
		{
			"name": "[concat(parameters('factoryName'), '/ds_sql_silver_as_vehiculos')]",
			"type": "Microsoft.DataFactory/factories/datasets",
			"apiVersion": "2018-06-01",
			"properties": {
				"linkedServiceName": {
					"referenceName": "ls_azure_sql_dw_dest",
					"type": "LinkedServiceReference"
				},
				"folder": {
					"name": "silver/AS"
				},
				"annotations": [],
				"type": "AzureSqlTable",
				"schema": [
					{
						"name": "vehiculo_id",
						"type": "int",
						"precision": 10
					},
					{
						"name": "transportista_id",
						"type": "int",
						"precision": 10
					},
					{
						"name": "descripcion",
						"type": "varchar"
					},
					{
						"name": "placa",
						"type": "varchar"
					},
					{
						"name": "tipo",
						"type": "varchar"
					},
					{
						"name": "capacidad_kg",
						"type": "decimal",
						"precision": 10,
						"scale": 2
					},
					{
						"name": "estado",
						"type": "varchar"
					}
				],
				"typeProperties": {
					"schema": "silver",
					"table": "as_vehiculos"
				}
			},
			"dependsOn": []
		},
		{
			"name": "[concat(parameters('factoryName'), '/ds_sql_silver_segip')]",
			"type": "Microsoft.DataFactory/factories/datasets",
			"apiVersion": "2018-06-01",
			"properties": {
				"linkedServiceName": {
					"referenceName": "ls_azure_sql_dw_dest",
					"type": "LinkedServiceReference"
				},
				"folder": {
					"name": "silver"
				},
				"annotations": [],
				"type": "AzureSqlTable",
				"schema": [
					{
						"name": "ci",
						"type": "varchar"
					},
					{
						"name": "nombres",
						"type": "varchar"
					},
					{
						"name": "apellido_paterno",
						"type": "varchar"
					},
					{
						"name": "apellido_materno",
						"type": "varchar"
					},
					{
						"name": "nombre_completo",
						"type": "varchar"
					},
					{
						"name": "fecha_nacimiento",
						"type": "date"
					},
					{
						"name": "genero",
						"type": "varchar"
					},
					{
						"name": "estado_civil",
						"type": "varchar"
					},
					{
						"name": "municipio",
						"type": "varchar"
					}
				],
				"typeProperties": {
					"schema": "silver",
					"table": "segip_ciudadanos"
				}
			},
			"dependsOn": []
		},
		{
			"name": "[concat(parameters('factoryName'), '/ds_sql_silver_sup_boletas')]",
			"type": "Microsoft.DataFactory/factories/datasets",
			"apiVersion": "2018-06-01",
			"properties": {
				"linkedServiceName": {
					"referenceName": "ls_azure_sql_dw_dest",
					"type": "LinkedServiceReference"
				},
				"folder": {
					"name": "silver/SUP"
				},
				"annotations": [],
				"type": "AzureSqlTable",
				"schema": [
					{
						"name": "boleta_id",
						"type": "int",
						"precision": 10
					},
					{
						"name": "control_id",
						"type": "int",
						"precision": 10
					},
					{
						"name": "ci_beneficiaria",
						"type": "varchar"
					},
					{
						"name": "nro_boleta",
						"type": "varchar"
					},
					{
						"name": "fecha_emision",
						"type": "date"
					},
					{
						"name": "estado",
						"type": "varchar"
					}
				],
				"typeProperties": {
					"schema": "silver",
					"table": "sup_boletas"
				}
			},
			"dependsOn": []
		},
		{
			"name": "[concat(parameters('factoryName'), '/ds_sql_silver_sup_catalogo_paquetes2')]",
			"type": "Microsoft.DataFactory/factories/datasets",
			"apiVersion": "2018-06-01",
			"properties": {
				"linkedServiceName": {
					"referenceName": "ls_azure_sql_dw_dest",
					"type": "LinkedServiceReference"
				},
				"folder": {
					"name": "silver/SUP"
				},
				"annotations": [],
				"type": "AzureSqlTable",
				"schema": [
					{
						"name": "paquete_id",
						"type": "int",
						"precision": 10
					},
					{
						"name": "nombre",
						"type": "varchar"
					},
					{
						"name": "contenido",
						"type": "varchar"
					},
					{
						"name": "peso_estandar_kg",
						"type": "decimal",
						"precision": 10,
						"scale": 2
					},
					{
						"name": "costo_estimado_bs",
						"type": "decimal",
						"precision": 10,
						"scale": 2
					},
					{
						"name": "fecha_procesamiento",
						"type": "datetime",
						"precision": 23,
						"scale": 3
					}
				],
				"typeProperties": {
					"schema": "silver",
					"table": "sup_paquetes"
				}
			},
			"dependsOn": []
		},
		{
			"name": "[concat(parameters('factoryName'), '/ds_sql_silver_sup_controles')]",
			"type": "Microsoft.DataFactory/factories/datasets",
			"apiVersion": "2018-06-01",
			"properties": {
				"linkedServiceName": {
					"referenceName": "ls_azure_sql_dw_dest",
					"type": "LinkedServiceReference"
				},
				"folder": {
					"name": "silver/SUP"
				},
				"annotations": [],
				"type": "AzureSqlTable",
				"schema": [
					{
						"name": "control_id",
						"type": "int",
						"precision": 10
					},
					{
						"name": "ci_beneficiaria",
						"type": "varchar"
					},
					{
						"name": "establecimiento_id",
						"type": "int",
						"precision": 10
					},
					{
						"name": "nro_control",
						"type": "int",
						"precision": 10
					},
					{
						"name": "fecha_control",
						"type": "date"
					},
					{
						"name": "semana_gestacion",
						"type": "int",
						"precision": 10
					},
					{
						"name": "peso_madre_kg",
						"type": "decimal",
						"precision": 5,
						"scale": 2
					},
					{
						"name": "presion_arterial",
						"type": "varchar"
					}
				],
				"typeProperties": {
					"schema": "silver",
					"table": "sup_controles"
				}
			},
			"dependsOn": []
		},
		{
			"name": "[concat(parameters('factoryName'), '/ds_sql_silver_sup_establecimientos2')]",
			"type": "Microsoft.DataFactory/factories/datasets",
			"apiVersion": "2018-06-01",
			"properties": {
				"linkedServiceName": {
					"referenceName": "ls_azure_sql_dw_dest",
					"type": "LinkedServiceReference"
				},
				"folder": {
					"name": "silver/SUP"
				},
				"annotations": [],
				"type": "AzureSqlTable",
				"schema": [
					{
						"name": "establecimiento_id",
						"type": "int",
						"precision": 10
					},
					{
						"name": "codigo_snis",
						"type": "varchar"
					},
					{
						"name": "nombre",
						"type": "varchar"
					},
					{
						"name": "tipo",
						"type": "varchar"
					},
					{
						"name": "nivel_atencion",
						"type": "varchar"
					},
					{
						"name": "municipio",
						"type": "varchar"
					},
					{
						"name": "departamento",
						"type": "varchar"
					},
					{
						"name": "red_salud",
						"type": "varchar"
					},
					{
						"name": "estado",
						"type": "varchar"
					},
					{
						"name": "fecha_procesamiento",
						"type": "datetime",
						"precision": 23,
						"scale": 3
					}
				],
				"typeProperties": {
					"schema": "silver",
					"table": "sup_establecimientos"
				}
			},
			"dependsOn": []
		},
		{
			"name": "[concat(parameters('factoryName'), '/ds_sql_silver_sup_inscripciones')]",
			"type": "Microsoft.DataFactory/factories/datasets",
			"apiVersion": "2018-06-01",
			"properties": {
				"linkedServiceName": {
					"referenceName": "ls_azure_sql_dw_dest",
					"type": "LinkedServiceReference"
				},
				"folder": {
					"name": "silver/SUP"
				},
				"annotations": [],
				"type": "AzureSqlTable",
				"schema": [
					{
						"name": "inscripcion_id",
						"type": "int",
						"precision": 10
					},
					{
						"name": "ci_beneficiaria",
						"type": "varchar"
					},
					{
						"name": "establecimiento_id",
						"type": "int",
						"precision": 10
					},
					{
						"name": "fecha_inscripcion",
						"type": "date"
					},
					{
						"name": "semana_gestacion",
						"type": "int",
						"precision": 10
					},
					{
						"name": "estado",
						"type": "varchar"
					}
				],
				"typeProperties": {
					"schema": "silver",
					"table": "sup_inscripciones"
				}
			},
			"dependsOn": []
		},
		{
			"name": "[concat(parameters('factoryName'), '/generico_bd')]",
			"type": "Microsoft.DataFactory/factories/datasets",
			"apiVersion": "2018-06-01",
			"properties": {
				"linkedServiceName": {
					"referenceName": "ls_azure_sql_dw_dest",
					"type": "LinkedServiceReference"
				},
				"annotations": [],
				"type": "AzureSqlTable",
				"schema": [],
				"typeProperties": {}
			},
			"dependsOn": []
		},
		{
			"name": "[concat(parameters('factoryName'), '/generico_bd_gold')]",
			"type": "Microsoft.DataFactory/factories/datasets",
			"apiVersion": "2018-06-01",
			"properties": {
				"linkedServiceName": {
					"referenceName": "ls_azure_sql_dw_dest",
					"type": "LinkedServiceReference"
				},
				"parameters": {
					"NombreTabla": {
						"type": "string"
					}
				},
				"annotations": [],
				"type": "AzureSqlTable",
				"schema": [
					{
						"name": "paquete_id",
						"type": "int",
						"precision": 10
					},
					{
						"name": "nombre_paquete",
						"type": "varchar"
					}
				],
				"typeProperties": {
					"schema": "gold",
					"table": {
						"value": "@dataset().NombreTabla",
						"type": "Expression"
					}
				}
			},
			"dependsOn": []
		},
		{
			"name": "[concat(parameters('factoryName'), '/generico_bd_silver')]",
			"type": "Microsoft.DataFactory/factories/datasets",
			"apiVersion": "2018-06-01",
			"properties": {
				"linkedServiceName": {
					"referenceName": "ls_azure_sql_dw_dest",
					"type": "LinkedServiceReference"
				},
				"parameters": {
					"NombreTabla": {
						"type": "string"
					}
				},
				"annotations": [],
				"type": "AzureSqlTable",
				"schema": [],
				"typeProperties": {
					"schema": "silver",
					"table": {
						"value": "@dataset().NombreTabla",
						"type": "Expression"
					}
				}
			},
			"dependsOn": []
		},
		{
			"name": "[concat(parameters('factoryName'), '/p_cargar_capa_bronze')]",
			"type": "Microsoft.DataFactory/factories/pipelines",
			"apiVersion": "2018-06-01",
			"properties": {
				"activities": [
					{
						"name": "Copy_SUP_Boletas",
						"type": "Copy",
						"dependsOn": [],
						"policy": {
							"timeout": "0.12:00:00",
							"retry": 0,
							"retryIntervalInSeconds": 30,
							"secureOutput": false,
							"secureInput": false
						},
						"userProperties": [],
						"typeProperties": {
							"source": {
								"type": "DelimitedTextSource",
								"storeSettings": {
									"type": "AzureBlobStorageReadSettings",
									"recursive": true,
									"enablePartitionDiscovery": false
								},
								"formatSettings": {
									"type": "DelimitedTextReadSettings"
								}
							},
							"sink": {
								"type": "AzureSqlSink",
								"writeBehavior": "insert",
								"sqlWriterUseTableLock": false
							},
							"enableStaging": false,
							"translator": {
								"type": "TabularTranslator",
								"mappings": [
									{
										"source": {
											"name": "boleta_id",
											"type": "String",
											"physicalType": "String"
										},
										"sink": {
											"name": "boleta_id",
											"type": "String",
											"physicalType": "varchar"
										}
									},
									{
										"source": {
											"name": "control_id",
											"type": "String",
											"physicalType": "String"
										},
										"sink": {
											"name": "control_id",
											"type": "String",
											"physicalType": "varchar"
										}
									},
									{
										"source": {
											"name": "ci_beneficiaria",
											"type": "String",
											"physicalType": "String"
										},
										"sink": {
											"name": "ci_beneficiaria",
											"type": "String",
											"physicalType": "varchar"
										}
									},
									{
										"source": {
											"name": "nro_boleta",
											"type": "String",
											"physicalType": "String"
										},
										"sink": {
											"name": "nro_boleta",
											"type": "String",
											"physicalType": "varchar"
										}
									},
									{
										"source": {
											"name": "fecha_emision",
											"type": "String",
											"physicalType": "String"
										},
										"sink": {
											"name": "fecha_emision",
											"type": "String",
											"physicalType": "varchar"
										}
									},
									{
										"source": {
											"name": "estado",
											"type": "String",
											"physicalType": "String"
										},
										"sink": {
											"name": "estado",
											"type": "String",
											"physicalType": "varchar"
										}
									}
								],
								"typeConversion": true,
								"typeConversionSettings": {
									"allowDataTruncation": true,
									"treatBooleanAsNumber": false
								}
							}
						},
						"inputs": [
							{
								"referenceName": "ds_csv_sup_boletas",
								"type": "DatasetReference",
								"parameters": {}
							}
						],
						"outputs": [
							{
								"referenceName": "ds_sql_bronze_sup_boletas",
								"type": "DatasetReference",
								"parameters": {}
							}
						]
					},
					{
						"name": "Copy_AS_Despachos",
						"type": "Copy",
						"dependsOn": [],
						"policy": {
							"timeout": "0.12:00:00",
							"retry": 0,
							"retryIntervalInSeconds": 30,
							"secureOutput": false,
							"secureInput": false
						},
						"userProperties": [],
						"typeProperties": {
							"source": {
								"type": "DelimitedTextSource",
								"storeSettings": {
									"type": "AzureBlobStorageReadSettings",
									"recursive": true,
									"enablePartitionDiscovery": false
								},
								"formatSettings": {
									"type": "DelimitedTextReadSettings"
								}
							},
							"sink": {
								"type": "AzureSqlSink",
								"writeBehavior": "insert",
								"sqlWriterUseTableLock": false
							},
							"enableStaging": false,
							"translator": {
								"type": "TabularTranslator",
								"mappings": [
									{
										"source": {
											"name": "despacho_id",
											"type": "String",
											"physicalType": "String"
										},
										"sink": {
											"name": "despacho_id",
											"type": "String",
											"physicalType": "varchar"
										}
									},
									{
										"source": {
											"name": "recepcion_id",
											"type": "String",
											"physicalType": "String"
										},
										"sink": {
											"name": "recepcion_id",
											"type": "String",
											"physicalType": "varchar"
										}
									},
									{
										"source": {
											"name": "nro_lote",
											"type": "String",
											"physicalType": "String"
										},
										"sink": {
											"name": "nro_lote",
											"type": "String",
											"physicalType": "varchar"
										}
									},
									{
										"source": {
											"name": "almacen_id",
											"type": "String",
											"physicalType": "String"
										},
										"sink": {
											"name": "almacen_id",
											"type": "String",
											"physicalType": "varchar"
										}
									},
									{
										"source": {
											"name": "transportista_id",
											"type": "String",
											"physicalType": "String"
										},
										"sink": {
											"name": "transportista_id",
											"type": "String",
											"physicalType": "varchar"
										}
									},
									{
										"source": {
											"name": "vehiculo_id",
											"type": "String",
											"physicalType": "String"
										},
										"sink": {
											"name": "vehiculo_id",
											"type": "String",
											"physicalType": "varchar"
										}
									},
									{
										"source": {
											"name": "fecha_despacho",
											"type": "String",
											"physicalType": "String"
										},
										"sink": {
											"name": "fecha_despacho",
											"type": "String",
											"physicalType": "varchar"
										}
									},
									{
										"source": {
											"name": "cantidad_despachada",
											"type": "String",
											"physicalType": "String"
										},
										"sink": {
											"name": "cantidad_despachada",
											"type": "String",
											"physicalType": "varchar"
										}
									},
									{
										"source": {
											"name": "centro_destino",
											"type": "String",
											"physicalType": "String"
										},
										"sink": {
											"name": "centro_destino",
											"type": "String",
											"physicalType": "varchar"
										}
									},
									{
										"source": {
											"name": "estado",
											"type": "String",
											"physicalType": "String"
										},
										"sink": {
											"name": "estado",
											"type": "String",
											"physicalType": "varchar"
										}
									},
									{
										"source": {
											"name": "responsable",
											"type": "String",
											"physicalType": "String"
										},
										"sink": {
											"name": "responsable",
											"type": "String",
											"physicalType": "varchar"
										}
									},
									{
										"source": {
											"name": "nro_guia_despacho",
											"type": "String",
											"physicalType": "String"
										},
										"sink": {
											"name": "nro_guia_despacho",
											"type": "String",
											"physicalType": "varchar"
										}
									},
									{
										"source": {
											"name": "fecha_llegada",
											"type": "String",
											"physicalType": "String"
										},
										"sink": {
											"name": "fecha_llegada",
											"type": "String",
											"physicalType": "varchar"
										}
									}
								],
								"typeConversion": true,
								"typeConversionSettings": {
									"allowDataTruncation": true,
									"treatBooleanAsNumber": false
								}
							}
						},
						"inputs": [
							{
								"referenceName": "ds_csv_as_despachos",
								"type": "DatasetReference",
								"parameters": {}
							}
						],
						"outputs": [
							{
								"referenceName": "ds_sql_bronze_as_despachos",
								"type": "DatasetReference",
								"parameters": {}
							}
						]
					},
					{
						"name": "Copy_SUP_Entregas2",
						"type": "Copy",
						"dependsOn": [],
						"policy": {
							"timeout": "0.12:00:00",
							"retry": 0,
							"retryIntervalInSeconds": 30,
							"secureOutput": false,
							"secureInput": false
						},
						"userProperties": [],
						"typeProperties": {
							"source": {
								"type": "DelimitedTextSource",
								"storeSettings": {
									"type": "AzureBlobStorageReadSettings",
									"recursive": true,
									"enablePartitionDiscovery": false
								},
								"formatSettings": {
									"type": "DelimitedTextReadSettings"
								}
							},
							"sink": {
								"type": "AzureSqlSink",
								"writeBehavior": "insert",
								"sqlWriterUseTableLock": false
							},
							"enableStaging": false,
							"translator": {
								"type": "TabularTranslator",
								"mappings": [
									{
										"source": {
											"name": "entrega_id",
											"type": "String",
											"physicalType": "String"
										},
										"sink": {
											"name": "entrega_id",
											"type": "String",
											"physicalType": "varchar"
										}
									},
									{
										"source": {
											"name": "boleta_id",
											"type": "String",
											"physicalType": "String"
										},
										"sink": {
											"name": "boleta_id",
											"type": "String",
											"physicalType": "varchar"
										}
									},
									{
										"source": {
											"name": "ci_beneficiaria",
											"type": "String",
											"physicalType": "String"
										},
										"sink": {
											"name": "ci_beneficiaria",
											"type": "String",
											"physicalType": "varchar"
										}
									},
									{
										"source": {
											"name": "establecimiento_id",
											"type": "String",
											"physicalType": "String"
										},
										"sink": {
											"name": "establecimiento_id",
											"type": "String",
											"physicalType": "varchar"
										}
									},
									{
										"source": {
											"name": "paquete_id",
											"type": "String",
											"physicalType": "String"
										},
										"sink": {
											"name": "paquete_id",
											"type": "String",
											"physicalType": "varchar"
										}
									},
									{
										"source": {
											"name": "paquete_nombre",
											"type": "String",
											"physicalType": "String"
										},
										"sink": {
											"name": "paquete_nombre",
											"type": "String",
											"physicalType": "varchar"
										}
									},
									{
										"source": {
											"name": "fecha_entrega",
											"type": "String",
											"physicalType": "String"
										},
										"sink": {
											"name": "fecha_entrega",
											"type": "String",
											"physicalType": "varchar"
										}
									},
									{
										"source": {
											"name": "lote_produccion",
											"type": "String",
											"physicalType": "String"
										},
										"sink": {
											"name": "lote_produccion",
											"type": "String",
											"physicalType": "varchar"
										}
									},
									{
										"source": {
											"name": "peso_paquete_kg",
											"type": "String",
											"physicalType": "String"
										},
										"sink": {
											"name": "peso_paquete_kg",
											"type": "String",
											"physicalType": "varchar"
										}
									},
									{
										"source": {
											"name": "fecha_proxima_entrega",
											"type": "String",
											"physicalType": "String"
										},
										"sink": {
											"name": "fecha_proxima_entrega",
											"type": "String",
											"physicalType": "varchar"
										}
									}
								],
								"typeConversion": true,
								"typeConversionSettings": {
									"allowDataTruncation": true,
									"treatBooleanAsNumber": false
								}
							}
						},
						"inputs": [
							{
								"referenceName": "ds_csv_sup_entregas",
								"type": "DatasetReference",
								"parameters": {}
							}
						],
						"outputs": [
							{
								"referenceName": "ds_sql_bronze_sup_entregas",
								"type": "DatasetReference",
								"parameters": {}
							}
						]
					},
					{
						"name": "Copy_SEGIP2",
						"type": "Copy",
						"dependsOn": [],
						"policy": {
							"timeout": "0.12:00:00",
							"retry": 0,
							"retryIntervalInSeconds": 30,
							"secureOutput": false,
							"secureInput": false
						},
						"userProperties": [],
						"typeProperties": {
							"source": {
								"type": "DelimitedTextSource",
								"storeSettings": {
									"type": "AzureBlobStorageReadSettings",
									"recursive": true,
									"enablePartitionDiscovery": false
								},
								"formatSettings": {
									"type": "DelimitedTextReadSettings"
								}
							},
							"sink": {
								"type": "AzureSqlSink",
								"preCopyScript": "TRUNCATE TABLE bronze.segip;",
								"writeBehavior": "insert",
								"sqlWriterUseTableLock": false,
								"disableMetricsCollection": false
							},
							"enableStaging": false,
							"translator": {
								"type": "TabularTranslator",
								"mappings": [
									{
										"source": {
											"name": "CI",
											"type": "String",
											"physicalType": "String"
										},
										"sink": {
											"name": "ci",
											"type": "String",
											"physicalType": "varchar"
										}
									},
									{
										"source": {
											"name": "Nombres",
											"type": "String",
											"physicalType": "String"
										},
										"sink": {
											"name": "nombres",
											"type": "String",
											"physicalType": "varchar"
										}
									},
									{
										"source": {
											"name": "Ap. Paterno",
											"type": "String",
											"physicalType": "String"
										},
										"sink": {
											"name": "apellido_paterno",
											"type": "String",
											"physicalType": "varchar"
										}
									},
									{
										"source": {
											"name": "Ap. Materno",
											"type": "String",
											"physicalType": "String"
										},
										"sink": {
											"name": "apellido_materno",
											"type": "String",
											"physicalType": "varchar"
										}
									},
									{
										"source": {
											"name": "Fecha Nac.",
											"type": "String",
											"physicalType": "String"
										},
										"sink": {
											"name": "fecha_nacimiento",
											"type": "String",
											"physicalType": "varchar"
										}
									},
									{
										"source": {
											"name": "Género",
											"type": "String",
											"physicalType": "String"
										},
										"sink": {
											"name": "genero",
											"type": "String",
											"physicalType": "varchar"
										}
									},
									{
										"source": {
											"name": "Estado Civil",
											"type": "String",
											"physicalType": "String"
										},
										"sink": {
											"name": "estado_civil",
											"type": "String",
											"physicalType": "varchar"
										}
									},
									{
										"source": {
											"name": "Municipio",
											"type": "String",
											"physicalType": "String"
										},
										"sink": {
											"name": "municipio",
											"type": "String",
											"physicalType": "varchar"
										}
									}
								],
								"typeConversion": true,
								"typeConversionSettings": {
									"allowDataTruncation": true,
									"treatBooleanAsNumber": false
								}
							}
						},
						"inputs": [
							{
								"referenceName": "ds_csv_segip",
								"type": "DatasetReference",
								"parameters": {}
							}
						],
						"outputs": [
							{
								"referenceName": "ds_sql_bronze_segip",
								"type": "DatasetReference",
								"parameters": {}
							}
						]
					},
					{
						"name": "Copy_SUP_Catalogo_Paquetes2",
						"type": "Copy",
						"dependsOn": [],
						"policy": {
							"timeout": "0.12:00:00",
							"retry": 0,
							"retryIntervalInSeconds": 30,
							"secureOutput": false,
							"secureInput": false
						},
						"userProperties": [],
						"typeProperties": {
							"source": {
								"type": "DelimitedTextSource",
								"storeSettings": {
									"type": "AzureBlobStorageReadSettings",
									"recursive": true,
									"enablePartitionDiscovery": false
								},
								"formatSettings": {
									"type": "DelimitedTextReadSettings"
								}
							},
							"sink": {
								"type": "AzureSqlSink",
								"preCopyScript": "TRUNCATE TABLE bronze.sup_catalogo_paquetes;",
								"writeBehavior": "insert",
								"sqlWriterUseTableLock": false,
								"disableMetricsCollection": false
							},
							"enableStaging": false,
							"translator": {
								"type": "TabularTranslator",
								"mappings": [
									{
										"source": {
											"name": "paquete_id",
											"type": "String",
											"physicalType": "String"
										},
										"sink": {
											"name": "paquete_id",
											"type": "Int32",
											"physicalType": "int"
										}
									},
									{
										"source": {
											"name": "nombre",
											"type": "String",
											"physicalType": "String"
										},
										"sink": {
											"name": "nombre",
											"type": "String",
											"physicalType": "varchar"
										}
									},
									{
										"source": {
											"name": "contenido",
											"type": "String",
											"physicalType": "String"
										},
										"sink": {
											"name": "contenido",
											"type": "String",
											"physicalType": "varchar"
										}
									},
									{
										"source": {
											"name": "peso_estandar_kg",
											"type": "String",
											"physicalType": "String"
										},
										"sink": {
											"name": "peso_estandar_kg",
											"type": "Decimal",
											"physicalType": "decimal",
											"scale": 2,
											"precision": 10
										}
									},
									{
										"source": {
											"name": "costo_estimado_bs",
											"type": "String",
											"physicalType": "String"
										},
										"sink": {
											"name": "costo_estimado_bs",
											"type": "Decimal",
											"physicalType": "decimal",
											"scale": 2,
											"precision": 10
										}
									}
								],
								"typeConversion": true,
								"typeConversionSettings": {
									"allowDataTruncation": true,
									"treatBooleanAsNumber": false
								}
							}
						},
						"inputs": [
							{
								"referenceName": "ds_csv_sup_catalogo_paquetes",
								"type": "DatasetReference",
								"parameters": {}
							}
						],
						"outputs": [
							{
								"referenceName": "ds_sql_bronze_sup_catalogo_paquetes2",
								"type": "DatasetReference",
								"parameters": {}
							}
						]
					},
					{
						"name": "Copy_SUP_Establecimientos2",
						"type": "Copy",
						"dependsOn": [],
						"policy": {
							"timeout": "0.12:00:00",
							"retry": 0,
							"retryIntervalInSeconds": 30,
							"secureOutput": false,
							"secureInput": false
						},
						"userProperties": [],
						"typeProperties": {
							"source": {
								"type": "DelimitedTextSource",
								"storeSettings": {
									"type": "AzureBlobStorageReadSettings",
									"recursive": true,
									"enablePartitionDiscovery": false
								},
								"formatSettings": {
									"type": "DelimitedTextReadSettings"
								}
							},
							"sink": {
								"type": "AzureSqlSink",
								"preCopyScript": "TRUNCATE TABLE bronze.sup_establecimientos;",
								"writeBehavior": "insert",
								"sqlWriterUseTableLock": false,
								"disableMetricsCollection": false
							},
							"enableStaging": false,
							"translator": {
								"type": "TabularTranslator",
								"mappings": [
									{
										"source": {
											"name": "establecimiento_id",
											"type": "String",
											"physicalType": "String"
										},
										"sink": {
											"name": "establecimiento_id",
											"type": "Int32",
											"physicalType": "int"
										}
									},
									{
										"source": {
											"name": "codigo_snis",
											"type": "String",
											"physicalType": "String"
										},
										"sink": {
											"name": "codigo_snis",
											"type": "String",
											"physicalType": "varchar"
										}
									},
									{
										"source": {
											"name": "nombre",
											"type": "String",
											"physicalType": "String"
										},
										"sink": {
											"name": "nombre",
											"type": "String",
											"physicalType": "varchar"
										}
									},
									{
										"source": {
											"name": "tipo",
											"type": "String",
											"physicalType": "String"
										},
										"sink": {
											"name": "tipo",
											"type": "String",
											"physicalType": "varchar"
										}
									},
									{
										"source": {
											"name": "nivel_atencion",
											"type": "String",
											"physicalType": "String"
										},
										"sink": {
											"name": "nivel_atencion",
											"type": "String",
											"physicalType": "varchar"
										}
									},
									{
										"source": {
											"name": "municipio",
											"type": "String",
											"physicalType": "String"
										},
										"sink": {
											"name": "municipio",
											"type": "String",
											"physicalType": "varchar"
										}
									},
									{
										"source": {
											"name": "departamento",
											"type": "String",
											"physicalType": "String"
										},
										"sink": {
											"name": "departamento",
											"type": "String",
											"physicalType": "varchar"
										}
									},
									{
										"source": {
											"name": "red_salud",
											"type": "String",
											"physicalType": "String"
										},
										"sink": {
											"name": "red_salud",
											"type": "String",
											"physicalType": "varchar"
										}
									},
									{
										"source": {
											"name": "estado",
											"type": "String",
											"physicalType": "String"
										},
										"sink": {
											"name": "estado",
											"type": "String",
											"physicalType": "varchar"
										}
									}
								],
								"typeConversion": true,
								"typeConversionSettings": {
									"allowDataTruncation": true,
									"treatBooleanAsNumber": false
								}
							}
						},
						"inputs": [
							{
								"referenceName": "ds_csv_sup_establecimientos",
								"type": "DatasetReference",
								"parameters": {}
							}
						],
						"outputs": [
							{
								"referenceName": "ds_sql_bronze_sup_establecimientos2",
								"type": "DatasetReference",
								"parameters": {}
							}
						]
					},
					{
						"name": "Copy_SUP_Controles",
						"type": "Copy",
						"dependsOn": [],
						"policy": {
							"timeout": "0.12:00:00",
							"retry": 0,
							"retryIntervalInSeconds": 30,
							"secureOutput": false,
							"secureInput": false
						},
						"userProperties": [],
						"typeProperties": {
							"source": {
								"type": "DelimitedTextSource",
								"storeSettings": {
									"type": "AzureBlobStorageReadSettings",
									"recursive": true,
									"enablePartitionDiscovery": false
								},
								"formatSettings": {
									"type": "DelimitedTextReadSettings"
								}
							},
							"sink": {
								"type": "AzureSqlSink",
								"writeBehavior": "insert",
								"sqlWriterUseTableLock": false
							},
							"enableStaging": false,
							"translator": {
								"type": "TabularTranslator",
								"mappings": [
									{
										"source": {
											"name": "control_id",
											"type": "String",
											"physicalType": "String"
										},
										"sink": {
											"name": "control_id",
											"type": "String",
											"physicalType": "varchar"
										}
									},
									{
										"source": {
											"name": "ci_beneficiaria",
											"type": "String",
											"physicalType": "String"
										},
										"sink": {
											"name": "ci_beneficiaria",
											"type": "String",
											"physicalType": "varchar"
										}
									},
									{
										"source": {
											"name": "establecimiento_id",
											"type": "String",
											"physicalType": "String"
										},
										"sink": {
											"name": "establecimiento_id",
											"type": "String",
											"physicalType": "varchar"
										}
									},
									{
										"source": {
											"name": "nro_control",
											"type": "String",
											"physicalType": "String"
										},
										"sink": {
											"name": "nro_control",
											"type": "String",
											"physicalType": "varchar"
										}
									},
									{
										"source": {
											"name": "fecha_control",
											"type": "String",
											"physicalType": "String"
										},
										"sink": {
											"name": "fecha_control",
											"type": "String",
											"physicalType": "varchar"
										}
									},
									{
										"source": {
											"name": "semana_gestacion",
											"type": "String",
											"physicalType": "String"
										},
										"sink": {
											"name": "semana_gestacion",
											"type": "String",
											"physicalType": "varchar"
										}
									},
									{
										"source": {
											"name": "peso_madre_kg",
											"type": "String",
											"physicalType": "String"
										},
										"sink": {
											"name": "peso_madre_kg",
											"type": "String",
											"physicalType": "varchar"
										}
									},
									{
										"source": {
											"name": "presion_arterial",
											"type": "String",
											"physicalType": "String"
										},
										"sink": {
											"name": "presion_arterial",
											"type": "String",
											"physicalType": "varchar"
										}
									}
								],
								"typeConversion": true,
								"typeConversionSettings": {
									"allowDataTruncation": true,
									"treatBooleanAsNumber": false
								}
							}
						},
						"inputs": [
							{
								"referenceName": "ds_csv_sup_controles",
								"type": "DatasetReference",
								"parameters": {}
							}
						],
						"outputs": [
							{
								"referenceName": "ds_sql_bronze_sup_controles",
								"type": "DatasetReference",
								"parameters": {}
							}
						]
					},
					{
						"name": "Copy_SUP_Inscripciones",
						"type": "Copy",
						"dependsOn": [],
						"policy": {
							"timeout": "0.12:00:00",
							"retry": 0,
							"retryIntervalInSeconds": 30,
							"secureOutput": false,
							"secureInput": false
						},
						"userProperties": [],
						"typeProperties": {
							"source": {
								"type": "DelimitedTextSource",
								"storeSettings": {
									"type": "AzureBlobStorageReadSettings",
									"recursive": true,
									"enablePartitionDiscovery": false
								},
								"formatSettings": {
									"type": "DelimitedTextReadSettings"
								}
							},
							"sink": {
								"type": "AzureSqlSink",
								"preCopyScript": "TRUNCATE TABLE bronze.sup_establecimientos;",
								"writeBehavior": "insert",
								"sqlWriterUseTableLock": false,
								"disableMetricsCollection": false
							},
							"enableStaging": false,
							"translator": {
								"type": "TabularTranslator",
								"mappings": [
									{
										"source": {
											"name": "inscripcion_id",
											"type": "String",
											"physicalType": "String"
										},
										"sink": {
											"name": "inscripcion_id",
											"type": "String",
											"physicalType": "varchar"
										}
									},
									{
										"source": {
											"name": "ci_beneficiaria",
											"type": "String",
											"physicalType": "String"
										},
										"sink": {
											"name": "ci_beneficiaria",
											"type": "String",
											"physicalType": "varchar"
										}
									},
									{
										"source": {
											"name": "establecimiento_id",
											"type": "String",
											"physicalType": "String"
										},
										"sink": {
											"name": "establecimiento_id",
											"type": "String",
											"physicalType": "varchar"
										}
									},
									{
										"source": {
											"name": "fecha_inscripcion",
											"type": "String",
											"physicalType": "String"
										},
										"sink": {
											"name": "fecha_inscripcion",
											"type": "String",
											"physicalType": "varchar"
										}
									},
									{
										"source": {
											"name": "semana_gestacion",
											"type": "String",
											"physicalType": "String"
										},
										"sink": {
											"name": "semana_gestacion",
											"type": "String",
											"physicalType": "varchar"
										}
									},
									{
										"source": {
											"name": "estado",
											"type": "String",
											"physicalType": "String"
										},
										"sink": {
											"name": "estado",
											"type": "String",
											"physicalType": "varchar"
										}
									}
								],
								"typeConversion": true,
								"typeConversionSettings": {
									"allowDataTruncation": true,
									"treatBooleanAsNumber": false
								}
							}
						},
						"inputs": [
							{
								"referenceName": "ds_csv_sup_inscripciones",
								"type": "DatasetReference",
								"parameters": {}
							}
						],
						"outputs": [
							{
								"referenceName": "ds_sql_bronze_sup_inscripciones",
								"type": "DatasetReference",
								"parameters": {}
							}
						]
					},
					{
						"name": "Copy_AS_Recepciones",
						"type": "Copy",
						"dependsOn": [],
						"policy": {
							"timeout": "0.12:00:00",
							"retry": 0,
							"retryIntervalInSeconds": 30,
							"secureOutput": false,
							"secureInput": false
						},
						"userProperties": [],
						"typeProperties": {
							"source": {
								"type": "DelimitedTextSource",
								"storeSettings": {
									"type": "AzureBlobStorageReadSettings",
									"recursive": true,
									"enablePartitionDiscovery": false
								},
								"formatSettings": {
									"type": "DelimitedTextReadSettings"
								}
							},
							"sink": {
								"type": "AzureSqlSink",
								"writeBehavior": "insert",
								"sqlWriterUseTableLock": false
							},
							"enableStaging": false,
							"translator": {
								"type": "TabularTranslator",
								"mappings": [
									{
										"source": {
											"name": "recepcion_id",
											"type": "String",
											"physicalType": "String"
										},
										"sink": {
											"name": "recepcion_id",
											"type": "String",
											"physicalType": "varchar"
										}
									},
									{
										"source": {
											"name": "nro_lote",
											"type": "String",
											"physicalType": "String"
										},
										"sink": {
											"name": "nro_lote",
											"type": "String",
											"physicalType": "varchar"
										}
									},
									{
										"source": {
											"name": "almacen_id",
											"type": "String",
											"physicalType": "String"
										},
										"sink": {
											"name": "almacen_id",
											"type": "String",
											"physicalType": "varchar"
										}
									},
									{
										"source": {
											"name": "transportista_id",
											"type": "String",
											"physicalType": "String"
										},
										"sink": {
											"name": "transportista_id",
											"type": "String",
											"physicalType": "varchar"
										}
									},
									{
										"source": {
											"name": "vehiculo_id",
											"type": "String",
											"physicalType": "String"
										},
										"sink": {
											"name": "vehiculo_id",
											"type": "String",
											"physicalType": "varchar"
										}
									},
									{
										"source": {
											"name": "fecha_recepcion",
											"type": "String",
											"physicalType": "String"
										},
										"sink": {
											"name": "fecha_recepcion",
											"type": "String",
											"physicalType": "varchar"
										}
									},
									{
										"source": {
											"name": "cantidad_recibida",
											"type": "String",
											"physicalType": "String"
										},
										"sink": {
											"name": "cantidad_recibida",
											"type": "String",
											"physicalType": "varchar"
										}
									},
									{
										"source": {
											"name": "unidad",
											"type": "String",
											"physicalType": "String"
										},
										"sink": {
											"name": "unidad",
											"type": "String",
											"physicalType": "varchar"
										}
									},
									{
										"source": {
											"name": "condicion",
											"type": "String",
											"physicalType": "String"
										},
										"sink": {
											"name": "condicion",
											"type": "String",
											"physicalType": "varchar"
										}
									},
									{
										"source": {
											"name": "estado",
											"type": "String",
											"physicalType": "String"
										},
										"sink": {
											"name": "estado",
											"type": "String",
											"physicalType": "varchar"
										}
									},
									{
										"source": {
											"name": "responsable",
											"type": "String",
											"physicalType": "String"
										},
										"sink": {
											"name": "responsable",
											"type": "String",
											"physicalType": "varchar"
										}
									},
									{
										"source": {
											"name": "nro_guia_remision",
											"type": "String",
											"physicalType": "String"
										},
										"sink": {
											"name": "nro_guia_remision",
											"type": "String",
											"physicalType": "varchar"
										}
									},
									{
										"source": {
											"name": "temperatura_llegada",
											"type": "String",
											"physicalType": "String"
										},
										"sink": {
											"name": "temperatura_llegada",
											"type": "String",
											"physicalType": "varchar"
										}
									}
								],
								"typeConversion": true,
								"typeConversionSettings": {
									"allowDataTruncation": true,
									"treatBooleanAsNumber": false
								}
							}
						},
						"inputs": [
							{
								"referenceName": "ds_csv_as_recepciones",
								"type": "DatasetReference",
								"parameters": {}
							}
						],
						"outputs": [
							{
								"referenceName": "ds_sql_bronze_as_recepciones",
								"type": "DatasetReference",
								"parameters": {}
							}
						]
					},
					{
						"name": "Copy_AS_almacenes",
						"type": "Copy",
						"dependsOn": [],
						"policy": {
							"timeout": "0.12:00:00",
							"retry": 0,
							"retryIntervalInSeconds": 30,
							"secureOutput": false,
							"secureInput": false
						},
						"userProperties": [],
						"typeProperties": {
							"source": {
								"type": "DelimitedTextSource",
								"storeSettings": {
									"type": "AzureBlobStorageReadSettings",
									"recursive": true,
									"enablePartitionDiscovery": false
								},
								"formatSettings": {
									"type": "DelimitedTextReadSettings"
								}
							},
							"sink": {
								"type": "AzureSqlSink",
								"writeBehavior": "insert",
								"sqlWriterUseTableLock": false
							},
							"enableStaging": false,
							"translator": {
								"type": "TabularTranslator",
								"mappings": [
									{
										"source": {
											"name": "almacen_id",
											"type": "String",
											"physicalType": "String"
										},
										"sink": {
											"name": "almacen_id",
											"type": "String",
											"physicalType": "varchar"
										}
									},
									{
										"source": {
											"name": "municipio",
											"type": "String",
											"physicalType": "String"
										},
										"sink": {
											"name": "municipio",
											"type": "String",
											"physicalType": "varchar"
										}
									},
									{
										"source": {
											"name": "nombre",
											"type": "String",
											"physicalType": "String"
										},
										"sink": {
											"name": "nombre",
											"type": "String",
											"physicalType": "varchar"
										}
									},
									{
										"source": {
											"name": "departamento",
											"type": "String",
											"physicalType": "String"
										},
										"sink": {
											"name": "departamento",
											"type": "String",
											"physicalType": "varchar"
										}
									},
									{
										"source": {
											"name": "direccion",
											"type": "String",
											"physicalType": "String"
										},
										"sink": {
											"name": "direccion",
											"type": "String",
											"physicalType": "varchar"
										}
									},
									{
										"source": {
											"name": "capacidad_m3",
											"type": "String",
											"physicalType": "String"
										},
										"sink": {
											"name": "capacidad_m3",
											"type": "String",
											"physicalType": "varchar"
										}
									},
									{
										"source": {
											"name": "estado",
											"type": "String",
											"physicalType": "String"
										},
										"sink": {
											"name": "estado",
											"type": "String",
											"physicalType": "varchar"
										}
									}
								],
								"typeConversion": true,
								"typeConversionSettings": {
									"allowDataTruncation": true,
									"treatBooleanAsNumber": false
								}
							}
						},
						"inputs": [
							{
								"referenceName": "ds_csv_as_almacenes",
								"type": "DatasetReference",
								"parameters": {}
							}
						],
						"outputs": [
							{
								"referenceName": "ds_sql_bronze_as_almacenes",
								"type": "DatasetReference",
								"parameters": {}
							}
						]
					},
					{
						"name": "Copy_AS_transportistas",
						"type": "Copy",
						"dependsOn": [],
						"policy": {
							"timeout": "0.12:00:00",
							"retry": 0,
							"retryIntervalInSeconds": 30,
							"secureOutput": false,
							"secureInput": false
						},
						"userProperties": [],
						"typeProperties": {
							"source": {
								"type": "DelimitedTextSource",
								"storeSettings": {
									"type": "AzureBlobStorageReadSettings",
									"recursive": true,
									"enablePartitionDiscovery": false
								},
								"formatSettings": {
									"type": "DelimitedTextReadSettings"
								}
							},
							"sink": {
								"type": "AzureSqlSink",
								"writeBehavior": "insert",
								"sqlWriterUseTableLock": false
							},
							"enableStaging": false,
							"translator": {
								"type": "TabularTranslator",
								"mappings": [
									{
										"source": {
											"name": "transportista_id",
											"type": "String",
											"physicalType": "String"
										},
										"sink": {
											"name": "transportista_id",
											"type": "String",
											"physicalType": "varchar"
										}
									},
									{
										"source": {
											"name": "razon_social",
											"type": "String",
											"physicalType": "String"
										},
										"sink": {
											"name": "razon_social",
											"type": "String",
											"physicalType": "varchar"
										}
									},
									{
										"source": {
											"name": "nit",
											"type": "String",
											"physicalType": "String"
										},
										"sink": {
											"name": "nit",
											"type": "String",
											"physicalType": "varchar"
										}
									},
									{
										"source": {
											"name": "municipio",
											"type": "String",
											"physicalType": "String"
										},
										"sink": {
											"name": "municipio",
											"type": "String",
											"physicalType": "varchar"
										}
									},
									{
										"source": {
											"name": "contacto",
											"type": "String",
											"physicalType": "String"
										},
										"sink": {
											"name": "contacto",
											"type": "String",
											"physicalType": "varchar"
										}
									},
									{
										"source": {
											"name": "telefono",
											"type": "String",
											"physicalType": "String"
										},
										"sink": {
											"name": "telefono",
											"type": "String",
											"physicalType": "varchar"
										}
									},
									{
										"source": {
											"name": "estado",
											"type": "String",
											"physicalType": "String"
										},
										"sink": {
											"name": "estado",
											"type": "String",
											"physicalType": "varchar"
										}
									}
								],
								"typeConversion": true,
								"typeConversionSettings": {
									"allowDataTruncation": true,
									"treatBooleanAsNumber": false
								}
							}
						},
						"inputs": [
							{
								"referenceName": "ds_csv_as_transportistas",
								"type": "DatasetReference",
								"parameters": {}
							}
						],
						"outputs": [
							{
								"referenceName": "ds_sql_bronze_as_transportistas",
								"type": "DatasetReference",
								"parameters": {}
							}
						]
					},
					{
						"name": "Copy_AS_vehiculos",
						"type": "Copy",
						"dependsOn": [],
						"policy": {
							"timeout": "0.12:00:00",
							"retry": 0,
							"retryIntervalInSeconds": 30,
							"secureOutput": false,
							"secureInput": false
						},
						"userProperties": [],
						"typeProperties": {
							"source": {
								"type": "DelimitedTextSource",
								"storeSettings": {
									"type": "AzureBlobStorageReadSettings",
									"recursive": true,
									"enablePartitionDiscovery": false
								},
								"formatSettings": {
									"type": "DelimitedTextReadSettings"
								}
							},
							"sink": {
								"type": "AzureSqlSink",
								"writeBehavior": "insert",
								"sqlWriterUseTableLock": false
							},
							"enableStaging": false,
							"translator": {
								"type": "TabularTranslator",
								"mappings": [
									{
										"source": {
											"name": "vehiculo_id",
											"type": "String",
											"physicalType": "String"
										},
										"sink": {
											"name": "vehiculo_id",
											"type": "String",
											"physicalType": "varchar"
										}
									},
									{
										"source": {
											"name": "transportista_id",
											"type": "String",
											"physicalType": "String"
										},
										"sink": {
											"name": "transportista_id",
											"type": "String",
											"physicalType": "varchar"
										}
									},
									{
										"source": {
											"name": "descripcion",
											"type": "String",
											"physicalType": "String"
										},
										"sink": {
											"name": "descripcion",
											"type": "String",
											"physicalType": "varchar"
										}
									},
									{
										"source": {
											"name": "placa",
											"type": "String",
											"physicalType": "String"
										},
										"sink": {
											"name": "placa",
											"type": "String",
											"physicalType": "varchar"
										}
									},
									{
										"source": {
											"name": "tipo",
											"type": "String",
											"physicalType": "String"
										},
										"sink": {
											"name": "tipo",
											"type": "String",
											"physicalType": "varchar"
										}
									},
									{
										"source": {
											"name": "capacidad_kg",
											"type": "String",
											"physicalType": "String"
										},
										"sink": {
											"name": "capacidad_kg",
											"type": "String",
											"physicalType": "varchar"
										}
									},
									{
										"source": {
											"name": "estado",
											"type": "String",
											"physicalType": "String"
										},
										"sink": {
											"name": "estado",
											"type": "String",
											"physicalType": "varchar"
										}
									}
								],
								"typeConversion": true,
								"typeConversionSettings": {
									"allowDataTruncation": true,
									"treatBooleanAsNumber": false
								}
							}
						},
						"inputs": [
							{
								"referenceName": "ds_csv_as_vehiculos",
								"type": "DatasetReference",
								"parameters": {}
							}
						],
						"outputs": [
							{
								"referenceName": "ds_sql_bronze_as_vehiculos",
								"type": "DatasetReference",
								"parameters": {}
							}
						]
					}
				],
				"policy": {
					"elapsedTimeMetric": {}
				},
				"annotations": [],
				"lastPublishTime": "2026-06-26T09:05:31Z"
			},
			"dependsOn": []
		},
		{
			"name": "[concat(parameters('factoryName'), '/df_bronze_to_silver_as_almacenes')]",
			"type": "Microsoft.DataFactory/factories/dataflows",
			"apiVersion": "2018-06-01",
			"properties": {
				"folder": {
					"name": "bronze_to_silver"
				},
				"type": "MappingDataFlow",
				"typeProperties": {
					"sources": [
						{
							"dataset": {
								"referenceName": "ds_sql_bronze_as_almacenes",
								"type": "DatasetReference"
							},
							"name": "source1"
						}
					],
					"sinks": [
						{
							"dataset": {
								"referenceName": "ds_sql_silver_as_almacenes",
								"type": "DatasetReference"
							},
							"name": "sink1"
						}
					],
					"transformations": [
						{
							"name": "derivedColumn1"
						}
					],
					"scriptLines": [
						"source(output(",
						"          almacen_id as string,",
						"          municipio as string,",
						"          nombre as string,",
						"          departamento as string,",
						"          direccion as string,",
						"          capacidad_m3 as string,",
						"          estado as string",
						"     ),",
						"     allowSchemaDrift: true,",
						"     validateSchema: false,",
						"     isolationLevel: 'READ_UNCOMMITTED',",
						"     format: 'table') ~> source1",
						"source1 derive(nombre = trim(nombre)) ~> derivedColumn1",
						"derivedColumn1 sink(allowSchemaDrift: true,",
						"     validateSchema: false,",
						"     input(",
						"          almacen_id as integer,",
						"          municipio as string,",
						"          nombre as string,",
						"          departamento as string,",
						"          direccion as string,",
						"          capacidad_m3 as decimal(10,2),",
						"          estado as string",
						"     ),",
						"     deletable:false,",
						"     insertable:true,",
						"     updateable:false,",
						"     upsertable:false,",
						"     truncate:true,",
						"     format: 'table',",
						"     skipDuplicateMapInputs: true,",
						"     skipDuplicateMapOutputs: true,",
						"     errorHandlingOption: 'stopOnFirstError',",
						"     mapColumn(",
						"          almacen_id,",
						"          municipio,",
						"          nombre,",
						"          departamento,",
						"          direccion,",
						"          capacidad_m3,",
						"          estado",
						"     )) ~> sink1"
					]
				}
			},
			"dependsOn": []
		},
		{
			"name": "[concat(parameters('factoryName'), '/df_bronze_to_silver_as_recepciones')]",
			"type": "Microsoft.DataFactory/factories/dataflows",
			"apiVersion": "2018-06-01",
			"properties": {
				"folder": {
					"name": "bronze_to_silver"
				},
				"type": "MappingDataFlow",
				"typeProperties": {
					"sources": [
						{
							"dataset": {
								"referenceName": "ds_sql_bronze_as_recepciones",
								"type": "DatasetReference"
							},
							"name": "source1"
						}
					],
					"sinks": [
						{
							"dataset": {
								"referenceName": "ds_sql_silver_as_recepciones",
								"type": "DatasetReference"
							},
							"name": "sink1"
						}
					],
					"transformations": [
						{
							"name": "derivedColumn1"
						}
					],
					"scriptLines": [
						"source(output(",
						"          recepcion_id as string,",
						"          nro_lote as string,",
						"          almacen_id as string,",
						"          transportista_id as string,",
						"          vehiculo_id as string,",
						"          fecha_recepcion as string,",
						"          cantidad_recibida as string,",
						"          unidad as string,",
						"          condicion as string,",
						"          estado as string,",
						"          responsable as string,",
						"          nro_guia_remision as string,",
						"          temperatura_llegada as string",
						"     ),",
						"     allowSchemaDrift: true,",
						"     validateSchema: false,",
						"     isolationLevel: 'READ_UNCOMMITTED',",
						"     format: 'table') ~> source1",
						"source1 derive(recepcion_id = toInteger(recepcion_id),",
						"          fecha_recepcion = iif(     instr(fecha_recepcion, '/') > 0,     toDate(fecha_recepcion, 'dd/MM/yyyy'),     iif(         instr(fecha_recepcion, '-') == 3,         toDate(fecha_recepcion, 'dd-MM-yyyy'),         toDate(fecha_recepcion, 'yyyy-MM-dd')     ) ),",
						"          cantidad_recibida = toDecimal(cantidad_recibida, 18, 2),",
						"          temperatura_llegada = toDecimal(temperatura_llegada, 5, 2),",
						"          almacen_id = toInteger(almacen_id),",
						"          transportista_id = toInteger(transportista_id),",
						"          vehiculo_id = toInteger(vehiculo_id)) ~> derivedColumn1",
						"derivedColumn1 sink(allowSchemaDrift: true,",
						"     validateSchema: false,",
						"     input(",
						"          recepcion_id as integer,",
						"          nro_lote as string,",
						"          condicion as string,",
						"          estado as string,",
						"          almacen_id as integer,",
						"          transportista_id as integer,",
						"          vehiculo_id as integer,",
						"          fecha_recepcion as date,",
						"          cantidad_recibida as decimal(18,2),",
						"          unidad as string,",
						"          responsable as string,",
						"          nro_guia_remision as string,",
						"          temperatura_llegada as decimal(5,2)",
						"     ),",
						"     deletable:false,",
						"     insertable:true,",
						"     updateable:false,",
						"     upsertable:false,",
						"     truncate:true,",
						"     format: 'table',",
						"     skipDuplicateMapInputs: true,",
						"     skipDuplicateMapOutputs: true,",
						"     errorHandlingOption: 'stopOnFirstError',",
						"     mapColumn(",
						"          recepcion_id,",
						"          nro_lote,",
						"          condicion,",
						"          estado,",
						"          almacen_id,",
						"          transportista_id,",
						"          vehiculo_id,",
						"          fecha_recepcion,",
						"          cantidad_recibida,",
						"          unidad,",
						"          responsable,",
						"          nro_guia_remision,",
						"          temperatura_llegada",
						"     )) ~> sink1"
					]
				}
			},
			"dependsOn": [
				"[concat(variables('factoryId'), '/datasets/ds_sql_silver_as_recepciones')]"
			]
		},
		{
			"name": "[concat(parameters('factoryName'), '/df_bronze_to_silver_as_vehiculos')]",
			"type": "Microsoft.DataFactory/factories/dataflows",
			"apiVersion": "2018-06-01",
			"properties": {
				"folder": {
					"name": "bronze_to_silver"
				},
				"type": "MappingDataFlow",
				"typeProperties": {
					"sources": [
						{
							"dataset": {
								"referenceName": "ds_sql_bronze_as_vehiculos",
								"type": "DatasetReference"
							},
							"name": "source1"
						}
					],
					"sinks": [
						{
							"dataset": {
								"referenceName": "ds_sql_silver_as_vehiculos",
								"type": "DatasetReference"
							},
							"name": "sink1"
						}
					],
					"transformations": [
						{
							"name": "derivedColumn1"
						}
					],
					"scriptLines": [
						"source(output(",
						"          vehiculo_id as string,",
						"          transportista_id as string,",
						"          descripcion as string,",
						"          placa as string,",
						"          tipo as string,",
						"          capacidad_kg as string,",
						"          estado as string",
						"     ),",
						"     allowSchemaDrift: true,",
						"     validateSchema: false,",
						"     isolationLevel: 'READ_UNCOMMITTED',",
						"     format: 'table') ~> source1",
						"source1 derive(vehiculo_id = toInteger(vehiculo_id),",
						"          transportista_id = toInteger(vehiculo_id),",
						"          capacidad_kg = toDecimal(capacidad_kg, 10, 2),",
						"          placa = upper(trim(placa)),",
						"          tipo = upper(trim(tipo)),",
						"          estado = upper(trim(estado))) ~> derivedColumn1",
						"derivedColumn1 sink(allowSchemaDrift: true,",
						"     validateSchema: false,",
						"     input(",
						"          vehiculo_id as integer,",
						"          transportista_id as integer,",
						"          descripcion as string,",
						"          placa as string,",
						"          tipo as string,",
						"          capacidad_kg as decimal(10,2),",
						"          estado as string",
						"     ),",
						"     deletable:false,",
						"     insertable:true,",
						"     updateable:false,",
						"     upsertable:false,",
						"     truncate:true,",
						"     format: 'table',",
						"     skipDuplicateMapInputs: true,",
						"     skipDuplicateMapOutputs: true,",
						"     errorHandlingOption: 'stopOnFirstError',",
						"     mapColumn(",
						"          vehiculo_id,",
						"          transportista_id,",
						"          descripcion,",
						"          placa,",
						"          tipo,",
						"          capacidad_kg,",
						"          estado",
						"     )) ~> sink1"
					]
				}
			},
			"dependsOn": [
				"[concat(variables('factoryId'), '/datasets/ds_sql_silver_as_vehiculos')]"
			]
		},
		{
			"name": "[concat(parameters('factoryName'), '/df_bronze_to_silver_boletas')]",
			"type": "Microsoft.DataFactory/factories/dataflows",
			"apiVersion": "2018-06-01",
			"properties": {
				"folder": {
					"name": "bronze_to_silver"
				},
				"type": "MappingDataFlow",
				"typeProperties": {
					"sources": [
						{
							"dataset": {
								"referenceName": "ds_sql_bronze_sup_boletas",
								"type": "DatasetReference"
							},
							"name": "source1"
						}
					],
					"sinks": [
						{
							"dataset": {
								"referenceName": "ds_sql_silver_sup_boletas",
								"type": "DatasetReference"
							},
							"name": "sink1"
						}
					],
					"transformations": [
						{
							"name": "LimpiarDatos"
						},
						{
							"name": "aggregate1"
						}
					],
					"scriptLines": [
						"source(output(",
						"          boleta_id as string,",
						"          control_id as string,",
						"          ci_beneficiaria as string,",
						"          nro_boleta as string,",
						"          fecha_emision as string,",
						"          estado as string",
						"     ),",
						"     allowSchemaDrift: true,",
						"     validateSchema: false,",
						"     isolationLevel: 'READ_UNCOMMITTED',",
						"     format: 'table') ~> source1",
						"source1 derive(ci_beneficiaria = upper(     iif(rlike(regexReplace(ci_beneficiaria, '[-_]', ''), '^[A-Za-z]{2}\\\\d+'),         concat(substring(regexReplace(ci_beneficiaria, '[-_]', ''), 3, length(regexReplace(ci_beneficiaria, '[-_]', ''))-2), '-', substring(regexReplace(ci_beneficiaria, '[-_]', ''), 1, 2)),         iif(rlike(regexReplace(ci_beneficiaria, '[-_]', ''), '\\\\d+[A-Za-z]{2}$'),             concat(substring(regexReplace(ci_beneficiaria, '[-_]', ''), 1, length(regexReplace(ci_beneficiaria, '[-_]', ''))-2), '-', right(regexReplace(ci_beneficiaria, '[-_]', ''), 2)),             regexReplace(ci_beneficiaria, '[-_]', '')         )     ) ),",
						"          estado = initCap(trim(estado)),",
						"          fecha_emision = iif(isNull(fecha_emision) || trim(toString(fecha_emision)) == '',      toDate(null()),      iif(instr(fecha_emision, '/') > 0, toDate(fecha_emision, 'dd/MM/yyyy'),          iif(instr(fecha_emision, '-') == 3, toDate(fecha_emision, 'dd-MM-yyyy'),              toDate(fecha_emision, 'yyyy-MM-dd')         )     ) ),",
						"          boleta_id = toInteger(toString(boleta_id))) ~> LimpiarDatos",
						"LimpiarDatos aggregate(groupBy(boleta_id),",
						"     control_id = first(boleta_id),",
						"          ci_beneficiaria = first(ci_beneficiaria),",
						"          nro_boleta = first(nro_boleta),",
						"          fecha_emision = first(fecha_emision),",
						"          estado = first(estado)) ~> aggregate1",
						"aggregate1 sink(allowSchemaDrift: true,",
						"     validateSchema: false,",
						"     input(",
						"          boleta_id as integer,",
						"          control_id as integer,",
						"          ci_beneficiaria as string,",
						"          nro_boleta as string,",
						"          fecha_emision as date,",
						"          estado as string",
						"     ),",
						"     deletable:false,",
						"     insertable:true,",
						"     updateable:false,",
						"     upsertable:false,",
						"     truncate:true,",
						"     format: 'table',",
						"     preSQLs:['TRUNCATE TABLE silver.sup_boletas;'],",
						"     skipDuplicateMapInputs: true,",
						"     skipDuplicateMapOutputs: true,",
						"     errorHandlingOption: 'stopOnFirstError',",
						"     mapColumn(",
						"          boleta_id,",
						"          control_id,",
						"          ci_beneficiaria,",
						"          nro_boleta,",
						"          fecha_emision,",
						"          estado",
						"     )) ~> sink1"
					]
				}
			},
			"dependsOn": [
				"[concat(variables('factoryId'), '/datasets/ds_sql_silver_sup_boletas')]"
			]
		},
		{
			"name": "[concat(parameters('factoryName'), '/df_bronze_to_silver_catalogo_paquetes')]",
			"type": "Microsoft.DataFactory/factories/dataflows",
			"apiVersion": "2018-06-01",
			"properties": {
				"folder": {
					"name": "bronze_to_silver"
				},
				"type": "MappingDataFlow",
				"typeProperties": {
					"sources": [
						{
							"dataset": {
								"referenceName": "ds_csv_sup_catalogo_paquetes",
								"type": "DatasetReference"
							},
							"name": "source1"
						}
					],
					"sinks": [
						{
							"dataset": {
								"referenceName": "ds_sql_silver_sup_catalogo_paquetes2",
								"type": "DatasetReference"
							},
							"name": "sink1"
						}
					],
					"transformations": [
						{
							"name": "derivedColumn1"
						}
					],
					"scriptLines": [
						"source(output(",
						"          paquete_id as string,",
						"          nombre as string,",
						"          contenido as string,",
						"          peso_estandar_kg as string,",
						"          costo_estimado_bs as string",
						"     ),",
						"     allowSchemaDrift: true,",
						"     validateSchema: false,",
						"     ignoreNoFilesFound: false) ~> source1",
						"source1 derive(paquete_id = toInteger(toString(paquete_id)),",
						"          nombre = trim(nombre),",
						"          contenido = trim(contenido),",
						"          peso_estandar_kg = toDecimal(toString(peso_estandar_kg), 10, 2),",
						"          costo_estimado_bs = toDecimal(costo_estimado_bs, 10, 2),",
						"          fecha_procesamiento = currentTimestamp()) ~> derivedColumn1",
						"derivedColumn1 sink(allowSchemaDrift: true,",
						"     validateSchema: false,",
						"     input(",
						"          paquete_id as integer,",
						"          nombre as string,",
						"          contenido as string,",
						"          peso_estandar_kg as decimal(10,2),",
						"          costo_estimado_bs as decimal(10,2),",
						"          fecha_procesamiento as timestamp",
						"     ),",
						"     deletable:false,",
						"     insertable:true,",
						"     updateable:false,",
						"     upsertable:false,",
						"     truncate:true,",
						"     format: 'table',",
						"     skipDuplicateMapInputs: true,",
						"     skipDuplicateMapOutputs: true,",
						"     errorHandlingOption: 'stopOnFirstError',",
						"     mapColumn(",
						"          paquete_id,",
						"          nombre,",
						"          contenido,",
						"          peso_estandar_kg,",
						"          costo_estimado_bs,",
						"          fecha_procesamiento",
						"     )) ~> sink1"
					]
				}
			},
			"dependsOn": [
				"[concat(variables('factoryId'), '/datasets/ds_sql_silver_sup_catalogo_paquetes2')]"
			]
		},
		{
			"name": "[concat(parameters('factoryName'), '/df_bronze_to_silver_controles')]",
			"type": "Microsoft.DataFactory/factories/dataflows",
			"apiVersion": "2018-06-01",
			"properties": {
				"folder": {
					"name": "bronze_to_silver"
				},
				"type": "MappingDataFlow",
				"typeProperties": {
					"sources": [
						{
							"dataset": {
								"referenceName": "ds_sql_bronze_sup_controles",
								"type": "DatasetReference"
							},
							"name": "source1"
						}
					],
					"sinks": [
						{
							"dataset": {
								"referenceName": "ds_sql_silver_sup_controles",
								"type": "DatasetReference"
							},
							"name": "sink1"
						}
					],
					"transformations": [
						{
							"name": "derivedColumn1"
						}
					],
					"scriptLines": [
						"source(output(",
						"          control_id as string,",
						"          ci_beneficiaria as string,",
						"          establecimiento_id as string,",
						"          nro_control as string,",
						"          fecha_control as string,",
						"          semana_gestacion as string,",
						"          peso_madre_kg as string,",
						"          presion_arterial as string",
						"     ),",
						"     allowSchemaDrift: true,",
						"     validateSchema: false,",
						"     isolationLevel: 'READ_UNCOMMITTED',",
						"     format: 'table') ~> source1",
						"source1 derive(control_id = toInteger(control_id),",
						"          establecimiento_id = toInteger(establecimiento_id),",
						"          nro_control = toInteger(nro_control),",
						"          semana_gestacion = toInteger(semana_gestacion),",
						"          peso_madre_kg = toDecimal(peso_madre_kg, 5, 2),",
						"          fecha_control = iif(     instr(toString(fecha_control), '-') > 0,     toDate(toString(fecha_control), 'yyyy-MM-dd'),     iif(         toInteger(left(toString(fecha_control),2)) > 12,         toDate(toString(fecha_control), 'dd/MM/yyyy'),         toDate(toString(fecha_control), 'MM/dd/yyyy')     ) ),",
						"          ci_beneficiaria = upper(     iif(         rlike(regexReplace(ci_beneficiaria, '[-_]', ''), '^[A-Za-z]{2}\\\\d+'),         concat(             substring(                 regexReplace(ci_beneficiaria, '[-_]', ''),                 3,                 length(regexReplace(ci_beneficiaria, '[-_]', '')) - 2             ),             '-',             substring(                 regexReplace(ci_beneficiaria, '[-_]', ''),                 1,                 2             )         ),         iif(             rlike(regexReplace(ci_beneficiaria, '[-_]', ''), '\\\\d+[A-Za-z]{2}$'),             concat(                 substring(                     regexReplace(ci_beneficiaria, '[-_]', ''),                     1,                     length(regexReplace(ci_beneficiaria, '[-_]', '')) - 2                 ),                 '-',                 right(                     regexReplace(ci_beneficiaria, '[-_]', ''),                     2                 )             ),             regexReplace(ci_beneficiaria, '[-_]', '')         )     ) ),",
						"          presion_arterial = trim(presion_arterial)) ~> derivedColumn1",
						"derivedColumn1 sink(allowSchemaDrift: true,",
						"     validateSchema: false,",
						"     input(",
						"          control_id as integer,",
						"          ci_beneficiaria as string,",
						"          establecimiento_id as integer,",
						"          nro_control as integer,",
						"          fecha_control as date,",
						"          semana_gestacion as integer,",
						"          peso_madre_kg as decimal(5,2),",
						"          presion_arterial as string",
						"     ),",
						"     deletable:false,",
						"     insertable:true,",
						"     updateable:false,",
						"     upsertable:false,",
						"     truncate:true,",
						"     format: 'table',",
						"     skipDuplicateMapInputs: true,",
						"     skipDuplicateMapOutputs: true,",
						"     errorHandlingOption: 'stopOnFirstError',",
						"     mapColumn(",
						"          control_id,",
						"          ci_beneficiaria,",
						"          establecimiento_id,",
						"          nro_control,",
						"          fecha_control,",
						"          semana_gestacion,",
						"          peso_madre_kg,",
						"          presion_arterial",
						"     )) ~> sink1"
					]
				}
			},
			"dependsOn": [
				"[concat(variables('factoryId'), '/datasets/ds_sql_silver_sup_controles')]"
			]
		}
	]
}